MANIFEST.in
README.rst
setup.py
pynessus/__init__.py
pynessus/nessus.py
pynessus.egg-info/PKG-INFO
pynessus.egg-info/SOURCES.txt
pynessus.egg-info/dependency_links.txt
pynessus.egg-info/top_level.txt
pynessus/test/__init__.py
pynessus/test/test_nessus.py