Metadata-Version: 1.1
Name: pynessus
Version: 0.9
Summary: Library to talk to a remote Nessus 5 server that via its xmlrpc interface.
Home-page: https://github.com/attwad/pynessus
Author: attwad
Author-email: tmusoft@gmail.com
License: UNKNOWN
Platform: any
Classifier: Development Status :: 4 - Beta
Classifier: Intended Audience :: Developers
Classifier: Programming Language :: Python :: 3
Classifier: Topic :: Security
Classifier: Topic :: Software Development :: Libraries
Classifier: Topic :: System :: Networking
